pycunia/__init__.py
pycunia/binance.py
pycunia/client.py
pycunia/gdax.py
pycunia/tools.py
pycunia-0.1.2.dist-info/DESCRIPTION.rst
pycunia-0.1.2.dist-info/METADATA
pycunia-0.1.2.dist-info/RECORD
pycunia-0.1.2.dist-info/WHEEL
pycunia-0.1.2.dist-info/metadata.json
pycunia-0.1.2.dist-info/top_level.txt
