Metadata-Version: 2.0
Name: pycunia
Version: 0.1.2
Summary: UNKNOWN
Home-page: http://github.com/hengruo/pycunia
Author: Hengruo Zhang
Author-email: UNKNOWN
License: MIT
Platform: UNKNOWN
Requires-Dist: ujson
Requires-Dist: requests
